{
  "content": [
    {
      "content": null,
      "created": "2026-03-11T10:41:22.386995Z",
      "format": null,
      "hash": null,
      "hash_algorithm": null,
      "last_modified": "2026-03-11T10:41:22.386995Z",
      "mimetype": null,
      "name": "notebooks",
      "path": "notebooks",
      "size": null,
      "type": "directory",
      "writable": true
    },
    {
      "content": null,
      "created": "2026-03-11T10:39:47.611361Z",
      "format": null,
      "hash": null,
      "hash_algorithm": null,
      "last_modified": "2026-03-11T10:39:47.611361Z",
      "mimetype": null,
      "name": "data",
      "path": "data",
      "size": null,
      "type": "directory",
      "writable": true
    }
  ],
  "created": "2026-03-11T10:39:47.617779Z",
  "format": "json",
  "hash": null,
  "hash_algorithm": null,
  "last_modified": "2026-03-11T10:39:47.617779Z",
  "mimetype": null,
  "name": "",
  "path": "",
  "size": null,
  "type": "directory",
  "writable": true
}